fastapi_myauth/__init__.py
fastapi_myauth/auth.py
fastapi_myauth/config.py
fastapi_myauth/email.py
fastapi_myauth/security.py
fastapi_myauth/test_main.py
fastapi_myauth/api/__init__.py
fastapi_myauth/api/deps.py
fastapi_myauth/api/v1/__init__.py
fastapi_myauth/api/v1/login.py
fastapi_myauth/api/v1/users.py
fastapi_myauth/crud/__init__.py
fastapi_myauth/crud/base.py
fastapi_myauth/crud/crud_token.py
fastapi_myauth/crud/crud_user.py
fastapi_myauth/email-templates/build/confirm_email.html
fastapi_myauth/email-templates/build/magic_login.html
fastapi_myauth/email-templates/build/new_account.html
fastapi_myauth/email-templates/build/reset_password.html
fastapi_myauth/email-templates/build/test_email.html
fastapi_myauth/email-templates/build/web_contact_email.html
fastapi_myauth/email-templates/src/confirm_email.mjml
fastapi_myauth/email-templates/src/magic_login.mjml
fastapi_myauth/email-templates/src/new_account.mjml
fastapi_myauth/email-templates/src/reset_password.mjml
fastapi_myauth/email-templates/src/test_email.mjml
fastapi_myauth/email-templates/src/web_contact_email.mjml
fastapi_myauth/models/__init__.py
fastapi_myauth/models/emails.py
fastapi_myauth/models/msg.py
fastapi_myauth/models/token.py
fastapi_myauth/models/totp.py
fastapi_myauth/models/user.py
fastapi_myauth-1.3.2.dist-info/METADATA
fastapi_myauth-1.3.2.dist-info/WHEEL
fastapi_myauth-1.3.2.dist-info/licenses/LICENSE
fastapi_myauth-1.3.2.dist-info/RECORD
