Metadata-Version: 2.4
Name: fastapi_myauth
Version: 1.3.2
Summary: A flexible and secure authentication library for FastAPI.
License: MIT
License-File: LICENSE
Requires-Python: >=3.13
Requires-Dist: argon2-cffi
Requires-Dist: cryptography>=44.0.2
Requires-Dist: email-validator<3.0.0.0,>=2.1.1
Requires-Dist: emails>=0.6.0
Requires-Dist: fastapi[standard]==0.116.*
Requires-Dist: passlib[bcrypt]>=1.7.4
Requires-Dist: pydantic-settings
Requires-Dist: pyjwt>=2.10.0
Requires-Dist: python-multipart<1.0.0,>=0.0.7
Requires-Dist: sqlmodel==0.0.24
